splitmerge/__init__.py
splitmerge/split_merge.py
split_merge_dir-6.0.0.dist-info/METADATA
split_merge_dir-6.0.0.dist-info/WHEEL
split_merge_dir-6.0.0.dist-info/top_level.txt
split_merge_dir-6.0.0.dist-info/RECORD
